html_summary/__init__.py
html_summary/cli.py
html_summary/summary.py
html_summary-0.3.1.dist-info/LICENSE
html_summary-0.3.1.dist-info/METADATA
html_summary-0.3.1.dist-info/WHEEL
html_summary-0.3.1.dist-info/entry_points.txt
html_summary-0.3.1.dist-info/RECORD
