Metadata-Version: 2.1
Name: html_summary
Version: 0.3.1
Summary: 
Author: narumi
Author-email: toucans-cutouts0f@icloud.com
Requires-Python: >=3.10,<4.0
Classifier: Programming Language :: Python :: 3
Classifier: Programming Language :: Python :: 3.10
Classifier: Programming Language :: Python :: 3.11
Classifier: Programming Language :: Python :: 3.12
Requires-Dist: beautifulsoup4 (>=4.12.3,<5.0.0)
Requires-Dist: click (>=8.1.7,<9.0.0)
Requires-Dist: httpx (>=0.27.0,<0.28.0)
Requires-Dist: langchain (>=0.2.1,<0.3.0)
Requires-Dist: langchain-community (>=0.2.1,<0.3.0)
Requires-Dist: langchain-openai (>=0.1.8,<0.2.0)
Requires-Dist: langchain-text-splitters (>=0.2.0,<0.3.0)
Requires-Dist: loguru (>=0.7.2,<0.8.0)
Requires-Dist: lxml (>=5.2.1,<6.0.0)
Requires-Dist: pypdf (>=4.2.0,<5.0.0)
Requires-Dist: python-dotenv (>=1.0.1,<2.0.0)
